Metadata-Version: 1.1
Name: mongo-shelve
Version: 0.1
Summary: Persistent dictionaries based on mongoDB
Home-page: https://github.com/zeycus/mongo_shelve/
Author: Miguel Garcia Diaz (aka Zeycus)
Author-email: zeycus@gmail.com
License: MIT
Keywords: shelve persistent dictionary
Platform: UNKNOWN
Classifier: Development Status :: 3 - Alpha
Classifier: License :: OSI Approved :: MIT License
Classifier: Programming Language :: Python :: 3.5
Classifier: Topic :: Database
